LICENCE
MANIFEST.in
README.rst
setup.cfg
setup.py
gaspar/__init__.py
gaspar/client.py
gaspar/consumers.py
gaspar/core.py
gaspar/producers.py
gaspar.egg-info/PKG-INFO
gaspar.egg-info/SOURCES.txt
gaspar.egg-info/dependency_links.txt
gaspar.egg-info/entry_points.txt
gaspar.egg-info/not-zip-safe
gaspar.egg-info/requires.txt
gaspar.egg-info/top_level.txt