Metadata-Version: 1.0
Name: gaspar
Version: 1.0
Summary: gaspar eventlet zmq parallel worker
Home-page: http://github.com/jmoiron/gaspar
Author: Jason Moiron
Author-email: jmoiron@jmoiron.net
License: MIT
Keywords: eventlet zmq parallel prefork
Platform: UNKNOWN
Classifier: Development Status :: 4 - Beta
Classifier: License :: OSI Approved :: MIT License
Classifier: Intended Audience :: Developers
Classifier: Operating System :: POSIX
